{
  "openapi": "3.0.1",
  "info": {
    "title": "API-Day4",
    "version": "v1"
  },
  "paths": {
    "/api/Account/Login": {
      "post": {
        "tags": [
          "Account"
        ],
        "requestBody": {
          "content": {
            "application/json": {
              "schema": {
                "$ref": "#/components/schemas/UserDataDTO"
              }
            },
            "text/json": {
              "schema": {
                "$ref": "#/components/schemas/UserDataDTO"
              }
            },
            "application/*+json": {
              "schema": {
                "$ref": "#/components/schemas/UserDataDTO"
              }
            }
          }
        },
        "responses": {
          "200": {
            "description": "OK"
          }
        }
      }
    },
    "/api/Account/Register": {
      "post": {
        "tags": [
          "Account"
        ],
        "requestBody": {
          "content": {
            "application/json": {
              "schema": {
                "$ref": "#/components/schemas/UserDataDTO"
              }
            },
            "text/json": {
              "schema": {
                "$ref": "#/components/schemas/UserDataDTO"
              }
            },
            "application/*+json": {
              "schema": {
                "$ref": "#/components/schemas/UserDataDTO"
              }
            }
          }
        },
        "responses": {
          "200": {
            "description": "OK"
          }
        }
      }
    },
    "/api/Account/CreateAdmin": {
      "post": {
        "tags": [
          "Account"
        ],
        "responses": {
          "200": {
            "description": "OK"
          }
        }
      }
    },
    "/api/Account/StaticLogin": {
      "post": {
        "tags": [
          "Account"
        ],
        "requestBody": {
          "content": {
            "application/json": {
              "schema": {
                "$ref": "#/components/schemas/UserDataDTO"
              }
            },
            "text/json": {
              "schema": {
                "$ref": "#/components/schemas/UserDataDTO"
              }
            },
            "application/*+json": {
              "schema": {
                "$ref": "#/components/schemas/UserDataDTO"
              }
            }
          }
        },
        "responses": {
          "200": {
            "description": "OK"
          }
        }
      }
    },
    "/api/Account/Protected": {
      "get": {
        "tags": [
          "Account"
        ],
        "responses": {
          "200": {
            "description": "OK"
          }
        }
      }
    },
    "/api/Account/AdminProtected": {
      "get": {
        "tags": [
          "Account"
        ],
        "responses": {
          "200": {
            "description": "OK"
          }
        }
      }
    },
    "/api/Account/AdminOnly": {
      "get": {
        "tags": [
          "Account"
        ],
        "responses": {
          "200": {
            "description": "OK"
          }
        }
      }
    },
    "/api/Account/AdminOnlyBetter": {
      "get": {
        "tags": [
          "Account"
        ],
        "responses": {
          "200": {
            "description": "OK"
          }
        }
      }
    },
    "/api/Course": {
      "get": {
        "tags": [
          "Course"
        ],
        "responses": {
          "200": {
            "description": "OK"
          }
        }
      },
      "post": {
        "tags": [
          "Course"
        ],
        "requestBody": {
          "content": {
            "application/json": {
              "schema": {
                "$ref": "#/components/schemas/Course"
              }
            },
            "text/json": {
              "schema": {
                "$ref": "#/components/schemas/Course"
              }
            },
            "application/*+json": {
              "schema": {
                "$ref": "#/components/schemas/Course"
              }
            }
          }
        },
        "responses": {
          "200": {
            "description": "OK"
          }
        }
      }
    },
    "/api/Course/{id}": {
      "delete": {
        "tags": [
          "Course"
        ],
        "parameters": [
          {
            "name": "id",
            "in": "path",
            "required": true,
            "schema": {
              "type": "integer",
              "format": "int32"
            }
          }
        ],
        "responses": {
          "200": {
            "description": "OK"
          }
        }
      },
      "put": {
        "tags": [
          "Course"
        ],
        "parameters": [
          {
            "name": "id",
            "in": "path",
            "required": true,
            "schema": {
              "type": "integer",
              "format": "int32"
            }
          }
        ],
        "requestBody": {
          "content": {
            "application/json": {
              "schema": {
                "$ref": "#/components/schemas/Course"
              }
            },
            "text/json": {
              "schema": {
                "$ref": "#/components/schemas/Course"
              }
            },
            "application/*+json": {
              "schema": {
                "$ref": "#/components/schemas/Course"
              }
            }
          }
        },
        "responses": {
          "200": {
            "description": "OK"
          }
        }
      },
      "get": {
        "tags": [
          "Course"
        ],
        "parameters": [
          {
            "name": "id",
            "in": "path",
            "required": true,
            "schema": {
              "type": "integer",
              "format": "int32"
            }
          }
        ],
        "responses": {
          "200": {
            "description": "OK"
          }
        }
      }
    },
    "/api/Course/name/{name}": {
      "get": {
        "tags": [
          "Course"
        ],
        "parameters": [
          {
            "name": "name",
            "in": "path",
            "required": true,
            "schema": {
              "type": "string"
            }
          }
        ],
        "responses": {
          "200": {
            "description": "OK"
          }
        }
      }
    },
    "/api/Course/AdminStats": {
      "get": {
        "tags": [
          "Course"
        ],
        "responses": {
          "200": {
            "description": "OK"
          }
        }
      }
    },
    "/api/Department/Customize Serialization": {
      "get": {
        "tags": [
          "Department"
        ],
        "responses": {
          "200": {
            "description": "OK"
          }
        }
      }
    },
    "/api/Department/Using Dto": {
      "get": {
        "tags": [
          "Department"
        ],
        "responses": {
          "200": {
            "description": "OK"
          }
        }
      }
    },
    "/api/Department": {
      "get": {
        "tags": [
          "Department"
        ],
        "responses": {
          "200": {
            "description": "OK"
          }
        }
      }
    }
  },
  "components": {
    "schemas": {
      "Course": {
        "required": [
          "crs_Name",
          "duration"
        ],
        "type": "object",
        "properties": {
          "id": {
            "type": "integer",
            "format": "int32"
          },
          "crs_Name": {
            "maxLength": 50,
            "minLength": 1,
            "type": "string"
          },
          "crs_Description": {
            "maxLength": 150,
            "type": "string",
            "nullable": true
          },
          "duration": {
            "type": "integer",
            "format": "int32"
          },
          "departmentId": {
            "type": "integer",
            "format": "int32"
          },
          "department": {
            "$ref": "#/components/schemas/Department"
          }
        },
        "additionalProperties": false
      },
      "Department": {
        "required": [
          "name"
        ],
        "type": "object",
        "properties": {
          "id": {
            "type": "integer",
            "format": "int32"
          },
          "name": {
            "minLength": 1,
            "type": "string"
          },
          "courses": {
            "type": "array",
            "items": {
              "$ref": "#/components/schemas/Course"
            },
            "nullable": true
          }
        },
        "additionalProperties": false
      },
      "UserDataDTO": {
        "type": "object",
        "properties": {
          "userName": {
            "type": "string",
            "nullable": true
          },
          "password": {
            "type": "string",
            "nullable": true
          }
        },
        "additionalProperties": false
      }
    },
    "securitySchemes": {
      "Bearer": {
        "type": "apiKey",
        "description": "JWT Authorization header using the Bearer scheme. Enter 'Bearer' [space] and then your token in the text input below.",
        "name": "Authorization",
        "in": "header"
      }
    }
  },
  "security": [
    {
      "Bearer": [ ]
    }
  ]
}